anime_scraper/__init__.py
anime_scraper/base.py
anime_scraper/browser_manager.py
anime_scraper/constants.py
anime_scraper/exceptions.py
anime_scraper/schemas.py
anime_scraper/utils.py
anime_scraper/scrapers/__init__.py
anime_scraper/scrapers/animeflv/__init__.py
anime_scraper/scrapers/animeflv/constants.py
anime_scraper/scrapers/animeflv/file_link.py
anime_scraper/scrapers/animeflv/scraper.py
anime_scraper/scrapers/animeflv/tab_link.py
anime_scraper/scrapers/animeflv/utils.py
anime_scraper/scrapers/jkanime/__init__.py
anime_scraper/scrapers/jkanime/constants.py
anime_scraper/scrapers/jkanime/file_link.py
anime_scraper/scrapers/jkanime/scraper.py
py_anime_scraper-1.0.4.dist-info/licenses/LICENSE
py_anime_scraper-1.0.4.dist-info/METADATA
py_anime_scraper-1.0.4.dist-info/WHEEL
py_anime_scraper-1.0.4.dist-info/top_level.txt
py_anime_scraper-1.0.4.dist-info/RECORD
