Metadata-Version: 2.4
Name: py-anime-scraper
Version: 1.0.4
Summary: Async-first Python library for scraping anime websites, currently supporting AnimeFLV
Author-email: "github:ElPitagoras14" <jonfrgar@espol.edu.ec>
License: MIT
Project-URL: Homepage, https://github.com/ElPitagoras14/py-anime-scraper
Project-URL: Repository, https://github.com/ElPitagoras14/py-anime-scraper
Keywords: anime,scraping,playwright,async,python
Classifier: Programming Language :: Python :: 3
Classifier: License :: OSI Approved :: MIT License
Classifier: Operating System :: OS Independent
Classifier: Topic :: Internet :: WWW/HTTP
Classifier: Topic :: Software Development :: Libraries :: Python Modules
Requires-Python: >=3.9
License-File: LICENSE
Requires-Dist: aiohttp
Requires-Dist: beautifulsoup4
Requires-Dist: playwright
Requires-Dist: lxml
Requires-Dist: loguru
Requires-Dist: curl_cffi
Provides-Extra: dev
Requires-Dist: pytest; extra == "dev"
Requires-Dist: pytest-asyncio; extra == "dev"
Requires-Dist: black; extra == "dev"
Requires-Dist: flake8; extra == "dev"
Requires-Dist: mypy; extra == "dev"
Requires-Dist: isort; extra == "dev"
Dynamic: license-file
